LICENSE
MANIFEST.in
README.md
setup.py
SecureMongoEngine.egg-info/PKG-INFO
SecureMongoEngine.egg-info/SOURCES.txt
SecureMongoEngine.egg-info/dependency_links.txt
SecureMongoEngine.egg-info/requires.txt
SecureMongoEngine.egg-info/top_level.txt
securemongoengine/__init__.py
securemongoengine/fields.py
securemongoengine/base/__init__.py
securemongoengine/base/exceptions.py
securemongoengine/base/fields.py
tests/__init__.py
tests/models.py
tests/test.py