Metadata-Version: 1.0
Name: SecureMongoEngine
Version: 0.1
Summary: It is a library for MongoEngine that you can use to encrypt certain fields of your models.
Home-page: https://github.com/juancho088/SecureMongoEngine
Author: Juan Urrego
Author-email: js.urrego@novcat.co
License: Apache License
Keywords: mongo mongoengine python secure encryption cypher pycrypto
Platform: UNKNOWN
